DAJIN2/__init__.py
DAJIN2/core/__init__.py
DAJIN2/core/classification/__init__.py
DAJIN2/core/classification/allele_merger.py
DAJIN2/core/classification/classifier.py
DAJIN2/core/clustering/__init__.py
DAJIN2/core/clustering/appender.py
DAJIN2/core/clustering/clustering.py
DAJIN2/core/clustering/kmer_generator.py
DAJIN2/core/clustering/label_extractor.py
DAJIN2/core/clustering/label_updator.py
DAJIN2/core/clustering/score_handler.py
DAJIN2/core/clustering/strand_bias_handler.py
DAJIN2/core/consensus/__init__.py
DAJIN2/core/consensus/clust_formatter.py
DAJIN2/core/consensus/consensus.py
DAJIN2/core/consensus/consensus_formatter.py
DAJIN2/core/consensus/consensus_mutation_analyzer.py
DAJIN2/core/consensus/similarity_searcher.py
DAJIN2/core/consensus/sv_annotator.py
DAJIN2/core/core.py
DAJIN2/core/preprocess/__init__.py
DAJIN2/core/preprocess/alignment/__init__.py
DAJIN2/core/preprocess/alignment/mapping.py
DAJIN2/core/preprocess/error_correction/__init__.py
DAJIN2/core/preprocess/error_correction/homopolymer_handler.py
DAJIN2/core/preprocess/error_correction/sequence_error_handler.py
DAJIN2/core/preprocess/error_correction/strand_bias_handler.py
DAJIN2/core/preprocess/external_integration/__init__.py
DAJIN2/core/preprocess/external_integration/midsv_caller.py
DAJIN2/core/preprocess/genome_coordinate/genome_coordinate_generator.py
DAJIN2/core/preprocess/genome_coordinate/genome_fetcher.py
DAJIN2/core/preprocess/infrastructure/__init__.py
DAJIN2/core/preprocess/infrastructure/directory_manager.py
DAJIN2/core/preprocess/infrastructure/input_formatter.py
DAJIN2/core/preprocess/mutation_processing/__init__.py
DAJIN2/core/preprocess/mutation_processing/anomaly_detector.py
DAJIN2/core/preprocess/mutation_processing/indel_counter.py
DAJIN2/core/preprocess/mutation_processing/indel_merger.py
DAJIN2/core/preprocess/mutation_processing/knockin_handler.py
DAJIN2/core/preprocess/mutation_processing/mutation_extractor.py
DAJIN2/core/preprocess/structural_variants/__init__.py
dajin2-0.7.4.dist-info/METADATA
dajin2-0.7.4.dist-info/WHEEL
dajin2-0.7.4.dist-info/entry_points.txt
dajin2-0.7.4.dist-info/licenses/LICENSE
dajin2-0.7.4.dist-info/RECORD
