Metadata-Version: 2.4
Name: DAJIN2
Version: 0.7.4
Summary: Comprehensive genotyping tool for targeted long-read sequencing analysis
License: MIT
License-File: LICENSE
Author: Akihiro Kuno
Author-email: akuno@md.tsukuba.ac.jp
Requires-Python: >=3.9,<3.13
Classifier: Intended Audience :: Science/Research
Classifier: License :: OSI Approved :: MIT License
Classifier: Operating System :: MacOS
Classifier: Operating System :: POSIX
Classifier: Programming Language :: Python :: 3
Classifier: Programming Language :: Python :: 3.9
Classifier: Programming Language :: Python :: 3.10
Classifier: Programming Language :: Python :: 3.11
Classifier: Programming Language :: Python :: 3.12
Classifier: Topic :: Scientific/Engineering :: Bio-Informatics
Requires-Dist: Flask (>=2.2.0)
Requires-Dist: Jinja2 (>=3.1.0)
Requires-Dist: cstag (>=1.0.0)
Requires-Dist: kaleido (>=0.2.0)
Requires-Dist: mappy (>=2.24)
Requires-Dist: midsv (==0.11.1)
Requires-Dist: numpy (>=1.24.0)
Requires-Dist: openpyxl (>=3.0.7)
Requires-Dist: pandas (>=2.0.0)
Requires-Dist: plotly (>=5.19.0)
Requires-Dist: pysam (>=0.21.0)
Requires-Dist: rapidfuzz (>=3.6.0)
Requires-Dist: scikit-learn (>=1.3.0)
Requires-Dist: scipy (>=1.10.0)
Requires-Dist: waitress (>=2.1.0)
Requires-Dist: wslPath (>=0.4.1)
Project-URL: Homepage, https://github.com/akikuno/DAJIN2
